intel_extension_for_pytorch/LICENSE
intel_extension_for_pytorch/_C.cpython-310-x86_64-linux-gnu.so
intel_extension_for_pytorch/__init__.py
intel_extension_for_pytorch/_init_on_device.py
intel_extension_for_pytorch/_isa_help.cpython-310-x86_64-linux-gnu.so
intel_extension_for_pytorch/_meta_registrations.py
intel_extension_for_pytorch/_version.py
intel_extension_for_pytorch/frontend.py
intel_extension_for_pytorch/launcher.py
intel_extension_for_pytorch/_dynamo/__init__.py
intel_extension_for_pytorch/_inductor/compile_fx.py
intel_extension_for_pytorch/_inductor/compiler.py
intel_extension_for_pytorch/_inductor/decomposition.py
intel_extension_for_pytorch/_inductor/ipex_fusion.py
intel_extension_for_pytorch/_inductor/ir.py
intel_extension_for_pytorch/_inductor/lowering.py
intel_extension_for_pytorch/_inductor/overrides.py
intel_extension_for_pytorch/_inductor/codegen/cpp.py
intel_extension_for_pytorch/bin/ipex_cpp_test
intel_extension_for_pytorch/cpu/__init__.py
intel_extension_for_pytorch/cpu/_auto_kernel_selection.py
intel_extension_for_pytorch/cpu/auto_ipex.py
intel_extension_for_pytorch/cpu/graph_capture.py
intel_extension_for_pytorch/cpu/onednn_fusion.py
intel_extension_for_pytorch/cpu/autocast/__init__.py
intel_extension_for_pytorch/cpu/autocast/_grad_scaler.py
intel_extension_for_pytorch/cpu/hypertune/__init__.py
intel_extension_for_pytorch/cpu/hypertune/__main__.py
intel_extension_for_pytorch/cpu/hypertune/objective.py
intel_extension_for_pytorch/cpu/hypertune/conf/__init__.py
intel_extension_for_pytorch/cpu/hypertune/conf/config.py
intel_extension_for_pytorch/cpu/hypertune/conf/dotdict.py
intel_extension_for_pytorch/cpu/hypertune/example/resnet50.py
intel_extension_for_pytorch/cpu/hypertune/strategy/__init__.py
intel_extension_for_pytorch/cpu/hypertune/strategy/grid.py
intel_extension_for_pytorch/cpu/hypertune/strategy/random.py
intel_extension_for_pytorch/cpu/hypertune/strategy/strategy.py
intel_extension_for_pytorch/cpu/launch/__init__.py
intel_extension_for_pytorch-2.8.0.dist-info/licenses/LICENSE
intel_extension_for_pytorch-2.8.0.dist-info/METADATA
intel_extension_for_pytorch-2.8.0.dist-info/WHEEL
intel_extension_for_pytorch-2.8.0.dist-info/entry_points.txt
intel_extension_for_pytorch-2.8.0.dist-info/top_level.txt
intel_extension_for_pytorch-2.8.0.dist-info/RECORD
