Metadata-Version: 2.4
Name: intel_extension_for_pytorch
Version: 2.8.0
Summary: Intel® Extension for PyTorch*
Home-page: https://github.com/intel/intel-extension-for-pytorch
Author: Intel Corp.
License: https://www.apache.org/licenses/LICENSE-2.0
Classifier: License :: OSI Approved :: Apache Software License
License-File: LICENSE
Requires-Dist: psutil
Requires-Dist: numpy
Requires-Dist: packaging
Dynamic: author
Dynamic: classifier
Dynamic: description
Dynamic: description-content-type
Dynamic: home-page
Dynamic: license
Dynamic: license-file
Dynamic: requires-dist
Dynamic: summary
